coba/__init__.py
coba/backports.py
coba/contexts.py
coba/encodings.py
coba/exceptions.py
coba/json.py
coba/multiprocessing.py
coba/primitives.py
coba/random.py
coba/register.py
coba/registry.py
coba/safety.py
coba/statistics.py
coba/utilities.py
coba/context/__init__.py
coba/context/cachers.py
coba/context/core.py
coba/context/loggers.py
coba/environments/__init__.py
coba/environments/core.py
coba/environments/filters.py
coba/environments/openml.py
coba/environments/results.py
coba/environments/serialized.py
coba/environments/supervised.py
coba/environments/synthetics.py
coba/environments/templates.py
coba/evaluators/__init__.py
coba/evaluators/offline.py
coba/evaluators/sequential.py
coba/experiments/__init__.py
coba/experiments/core.py
coba/experiments/process.py
coba/learners/__init__.py
coba/learners/bandit.py
coba/learners/corral.py
coba/learners/lints.py
coba/learners/linucb.py
coba/learners/misguided.py
coba/learners/utilities.py
coba/learners/vowpal.py
coba/pipes/__init__.py
coba/pipes/core.py
coba/pipes/filters.py
coba/pipes/lines.py
coba/pipes/multiprocessing.py
coba/pipes/readers.py
coba/pipes/rows.py
coba/pipes/sinks.py
coba/pipes/sources.py
coba/pipes/utilities.py
coba/results/__init__.py
coba/results/core.py
coba/results/errors.py
coba-8.0.5.dist-info/AUTHORS
coba-8.0.5.dist-info/LICENSE
coba-8.0.5.dist-info/METADATA
coba-8.0.5.dist-info/WHEEL
coba-8.0.5.dist-info/entry_points.txt
coba-8.0.5.dist-info/top_level.txt
coba-8.0.5.dist-info/RECORD
