Metadata-Version: 2.1
Name: coba
Version: 8.0.5
Summary: A contextual bandit research package
Author-email: Mark Rucker <rucker.mark@gmail.com>
License: BSD-3-Clause
Project-URL: Homepage, https://coba-docs.readthedocs.io/
Project-URL: Documentation, https://coba-docs.readthedocs.io/
Project-URL: Repository, https://github.com/vowpalwabbit/coba
Classifier: Intended Audience :: Science/Research
Classifier: License :: OSI Approved :: BSD License
Classifier: Programming Language :: Python :: 3.8
Classifier: Operating System :: OS Independent
Classifier: Topic :: Scientific/Engineering
Requires-Python: >=3.8
License-File: LICENSE
License-File: AUTHORS
Provides-Extra: full
Requires-Dist: vowpalwabbit ; extra == 'full'
Requires-Dist: pandas ; extra == 'full'
Requires-Dist: matplotlib ; extra == 'full'
Requires-Dist: numpy ; extra == 'full'
Requires-Dist: scipy ; extra == 'full'
Requires-Dist: cloudpickle ; extra == 'full'
Requires-Dist: torch ; extra == 'full'
